termination_handler/__init__.py
termination_handler/termination_handler.py
termination_handler/handlers/__init__.py
termination_handler/handlers/handler.py
termination_handler/handlers/k8s_handler.py
termination_handler/handlers/nomad_handler.py
termination_handler/handlers/slack_handler.py
termination_handler-0.0.5.dist-info/LICENSE.md
termination_handler-0.0.5.dist-info/METADATA
termination_handler-0.0.5.dist-info/WHEEL
termination_handler-0.0.5.dist-info/entry_points.txt
termination_handler-0.0.5.dist-info/top_level.txt
termination_handler-0.0.5.dist-info/RECORD
