Metadata-Version: 2.1
Name: termination-handler
Version: 0.0.5
Summary: Handle termination notices on spot/preemptible instances.
Home-page: https://github.com/dgzlopes/termination-handler
Author: Daniel González Lopes
Author-email: danielgonzalezlopes@gmail.com
License: MIT
Platform: UNKNOWN
Classifier: Development Status :: 3 - Alpha
Classifier: Intended Audience :: Developers
Classifier: Natural Language :: English
Classifier: Programming Language :: Python :: 3.6
Classifier: Programming Language :: Python :: 3.7
Classifier: License :: OSI Approved :: MIT License
Classifier: Topic :: Software Development :: Libraries :: Python Modules
Classifier: Topic :: System :: Systems Administration
Classifier: Topic :: System :: Networking
Requires-Dist: requests
Requires-Dist: cloud-detect
Requires-Dist: slackclient
